notion_api_client/__init__.py
notion_api_client/main.py
notion_api_client-0.0.2.dist-info/METADATA
notion_api_client-0.0.2.dist-info/WHEEL
notion_api_client-0.0.2.dist-info/licenses/LICENSE
notion_api_client-0.0.2.dist-info/RECORD
