Metadata-Version: 2.3
Name: notion-api-client
Version: 0.0.2
Author: Artem Shershnev
License-File: LICENSE
Classifier: License :: OSI Approved :: MIT License
Classifier: Operating System :: OS Independent
Classifier: Programming Language :: Python :: 3
Requires-Python: >=3.9.6
Requires-Dist: requests>=2.31.0
